cowinapi_by_ishaan
