Metadata-Version: 2.1
Name: cowinapi-by-ishaan
Version: 0.0.2
Summary: Vaccine availability
Home-page: https://in.linkedin.com/in/ishaangupta1201
Author: Ishaan Gupta
Author-email: solotechfeedback@gmail.com
License: Apache License 2.0
Keywords: cowin,covid,vaccine,vaccine booking,cowin registrarion,python cowin,cowin pip
Platform: UNKNOWN
Classifier: Development Status :: 5 - Production/Stable
Classifier: Intended Audience :: Developers
Classifier: Operating System :: Microsoft :: Windows :: Windows 10
Classifier: License :: OSI Approved :: Apache Software License
Classifier: Programming Language :: Python :: 3
Classifier: Topic :: Internet
Requires-Python: >=3.6,<4
